main.py
setup.py
bytedplus_rec.egg-info/PKG-INFO
bytedplus_rec.egg-info/SOURCES.txt
bytedplus_rec.egg-info/dependency_links.txt
bytedplus_rec.egg-info/requires.txt
bytedplus_rec.egg-info/top_level.txt